radhesh_algos/__init__.py
radhesh_algos/ao_star.py
radhesh_algos/astar.py
radhesh_algos/bfs.py
radhesh_algos/climbing.py
radhesh_algos/dfs.py
radhesh_algos/dfs_id.py
radhesh_algos/dfs_limited.py
radhesh_algos/steepest_ascent.py
radhesh_algos/water_jug.py
radhesh_algos-0.1.dist-info/METADATA
radhesh_algos-0.1.dist-info/WHEEL
radhesh_algos-0.1.dist-info/top_level.txt
radhesh_algos-0.1.dist-info/RECORD
