Metadata-Version: 2.1
Name: radhesh-algos
Version: 0.1
Summary: Python library for search algorithms and problem-solving techniques
Author: Radhesh Goel
Author-email: radhesh036916@gmail.com
License: MIT
